Workbook

Sheet Overview
B2: Union App — Pricing Model
B4: Prepared for: | C4: CUPE / PSAC National Unions
B5: Prepared by: | C5: Nungisa Law
B6: Date: | C6: April 02, 2026
B7: Currency: | C7: CAD ($)
B9: Model Structure
B10: This model prices a national union app license with per-member tiered pricing, regional deployment add-ons, implementation fees, and a full breakeven analysis. All blue-text cells are editable inputs — change them to run scenarios.
B12: Sheet Index
B13: Sheet | C13: Description
B14: Assumptions | C14: All input assumptions (costs, margins, growth)
B15: Tier Pricing | C15: Per-member pricing across 4 tiers and member bands
B16: Regional Deploy | C16: Per-region deployment costs and add-ons
B17: Revenue Model | C17: 3-year revenue projection by customer scenario
B18: Breakeven | C18: Fixed/variable cost breakeven analysis with chart
B21: Note: Blue text = editable inputs. Black text = formulas. Green text = cross-sheet links.
B22: Generated: 2026-04-02

Sheet Assumptions
B2: Input Assumptions
B4: Cost Structure (Annual)
B5: Item | C5: Value | D5: Unit | E5: Notes
B6: Cloud Hosting (base) | C6: 36000 | D6: $/yr | E6: AWS/Azure base infrastructure
B7: Cloud Hosting (per 1k members) | C7: 120 | D7: $/yr/1k | E7: Scales with member count
B8: Engineering Team (salaries) | C8: 480000 | D8: $/yr | E8: 4 FTE engineers avg $120k
B9: Product & Design | C9: 150000 | D9: $/yr | E9: PM + UX designer
B10: Customer Success / Support | C10: 120000 | D10: $/yr | E10: 2 FTE support staff
B11: Sales & Marketing | C11: 96000 | D11: $/yr | E11: 1 FTE + campaigns
B12: Legal & Compliance | C12: 36000 | D12: $/yr | E12: Privacy, labour law
B13: Admin & Overhead | C13: 60000 | D13: $/yr | E13: Office, tools, insurance
B14: Implementation Cost (per region) | C14: 3500 | D14: $/region | E14: Setup, migration, training
B15: Per-Member Variable Cost | C15: 0.15 | D15: $/member/mo | E15: Compute, storage, support load
B17: Total Fixed Costs (Annual) | C17: =C6+C8+C9+C10+C11+C12+C13 -> 978000
B19: Pricing Assumptions
B20: Parameter | C20: Value | D20: Unit | E20: Notes
B21: Target Gross Margin | C21: 0.75 | D21: % | E21: Industry standard B2B SaaS: 70-80%
B22: National License Base Fee | C22: 25000 | D22: $/yr | E22: Minimum annual platform fee
B23: Implementation Fee (per region) | C23: 5000 | D23: $/region | E23: One-time setup + migration
B24: Annual Price Escalator | C24: 0.03 | D24: %/yr | E24: Built into multi-year contracts
B25: Discount for 3-Year Contract | C25: 0.1 | D25: % | E25: Incentivize long-term commitment
B26: Discount for 50k+ Members | C26: 0.15 | D26: % | E26: Volume discount for large unions
B29: Market Sizing
B30: Parameter | C30: Value | D30: Unit | E30: Notes
B31: CUPE Members (approx) | C31: 700000 | D31: members | E31: Largest Canadian union
B32: PSAC Members (approx) | C32: 230000 | D32: members | E32: Federal public service
B33: Total CLC-Affiliated Members | C33: 3000000 | D33: members | E33: Canadian Labour Congress
B34: Addressable Market (Year 1) | C34: 0.05 | D34: % | E34: % of CLC membership targeted
B35: Addressable Market (Year 2) | C35: 0.1 | D35: % | E35: Growing adoption
B36: Addressable Market (Year 3) | C36: 0.18 | D36: % | E36: Maturation phase

Sheet Tier Pricing
B2: Per-Member Tier Pricing Matrix
B4: Tier Definitions
B5: Tier | C5: Member Band | D5: Per-Member / Mo | E5: Per-Member / Yr | F5: National Base Fee | G5: Features Included
B6: Starter | C6: 200 - 2,000 | D6: 4.5 | E6: =D6*12 -> 54 | F6: =Assumptions!C22 -> 25000 | G6: Core: grievances, membership, dues, basic reports
B7: Professional | C7: 2,001 - 15,000 | D7: 3.75 | E7: =D7*12 -> 45 | F7: =Assumptions!C22 -> 25000 | G7: All Starter + comms, scheduling, doc storage, analytics
B8: Premium | C8: 15,001 - 50,000 | D8: 2.95 | E8: =D8*12 -> 35.4 | F8: =Assumptions!C22 -> 25000 | G8: All Pro + advanced analytics, API, custom workflows, voting
B9: Enterprise | C9: 50,001 - 100,000+ | D9: 2.25 | E9: =D9*12 -> 27 | F9: =Assumptions!C22 -> 25000 | G9: All Premium + dedicated support, SLA, custom dev, white-label
B12: Annual Revenue Calculator
B13: Enter a member count below to see annual revenue for each tier (base fee + per-member).
B14: Scenario | C14: Members | D14: Starter | E14: Professional | F14: Premium | G14: Enterprise | H14: Impl. Fee (10 regions)
B15: Small Local | C15: 200 | D15: ='Tier Pricing'!F6+(C15*'Tier Pricing'!E6) -> 35800 | E15: ='Tier Pricing'!F7+(C15*'Tier Pricing'!E7) -> 34000 | F15: ='Tier Pricing'!F8+(C15*'Tier Pricing'!E8) -> 32080 | G15: ='Tier Pricing'!F9+(C15*'Tier Pricing'!E9) -> 30400 | H15: =10*Assumptions!C23 -> 50000
B16: Mid Local | C16: 2000 | D16: ='Tier Pricing'!F6+(C16*'Tier Pricing'!E6) -> 133000 | E16: ='Tier Pricing'!F7+(C16*'Tier Pricing'!E7) -> 115000 | F16: ='Tier Pricing'!F8+(C16*'Tier Pricing'!E8) -> 95800 | G16: ='Tier Pricing'!F9+(C16*'Tier Pricing'!E9) -> 79000 | H16: =10*Assumptions!C23 -> 50000
B17: Regional | C17: 10000 | D17: ='Tier Pricing'!F6+(C17*'Tier Pricing'!E6) -> 565000 | E17: ='Tier Pricing'!F7+(C17*'Tier Pricing'!E7) -> 475000 | F17: ='Tier Pricing'!F8+(C17*'Tier Pricing'!E8) -> 379000 | G17: ='Tier Pricing'!F9+(C17*'Tier Pricing'!E9) -> 295000 | H17: =10*Assumptions!C23 -> 50000
B18: Mid National | C18: 25000 | D18: ='Tier Pricing'!F6+(C18*'Tier Pricing'!E6) -> 1375000 | E18: ='Tier Pricing'!F7+(C18*'Tier Pricing'!E7) -> 1150000 | F18: ='Tier Pricing'!F8+(C18*'Tier Pricing'!E8) -> 910000 | G18: ='Tier Pricing'!F9+(C18*'Tier Pricing'!E9) -> 700000 | H18: =10*Assumptions!C23 -> 50000
B19: Large National (PSAC-size) | C19: 50000 | D19: ='Tier Pricing'!F6+(C19*'Tier Pricing'!E6) -> 2725000 | E19: ='Tier Pricing'!F7+(C19*'Tier Pricing'!E7) -> 2275000 | F19: ='Tier Pricing'!F8+(C19*'Tier Pricing'!E8) -> 1795000 | G19: ='Tier Pricing'!F9+(C19*'Tier Pricing'!E9) -> 1375000 | H19: =10*Assumptions!C23 -> 50000
B20: Mega National (CUPE-size) | C20: 100000 | D20: ='Tier Pricing'!F6+(C20*'Tier Pricing'!E6) -> 5425000 | E20: ='Tier Pricing'!F7+(C20*'Tier Pricing'!E7) -> 4525000 | F20: ='Tier Pricing'!F8+(C20*'Tier Pricing'!E8) -> 3565000 | G20: ='Tier Pricing'!F9+(C20*'Tier Pricing'!E9) -> 2725000 | H20: =10*Assumptions!C23 -> 50000
B23: Available Discounts
B24: Discount Type | C24: Rate | D24: Condition
B25: 3-Year Contract Lock-in | C25: =Assumptions!C25 -> 0.1 | D25: Committed multi-year agreement
B26: Volume (50k+ Members) | C26: =Assumptions!C26 -> 0.15 | D26: Applied on per-member rate only
B27: Early Adopter (Year 1) | C27: 0.05 | D27: First 3 national unions to sign

Sheet Regional Deploy
B2: Per-Region Deployment Model
B4: Canadian Regional Breakdown
B5: Province / Region | C5: Est. Locals | D5: Impl. Fee (One-Time) | E5: Annual Support | F5: Annual Hosting Add-On | G5: Total Year 1 | H5: Total Year 2+
B6: British Columbia | C6: 45 | D6: =Assumptions!C23 -> 5000 | E6: =2000+(C6*50) -> 4250 | F6: =C6*25 -> 1125 | G6: =D6+E6+F6 -> 10375 | H6: =E6+F6 -> 5375
B7: Alberta | C7: 30 | D7: =Assumptions!C23 -> 5000 | E7: =2000+(C7*50) -> 3500 | F7: =C7*25 -> 750 | G7: =D7+E7+F7 -> 9250 | H7: =E7+F7 -> 4250
B8: Saskatchewan | C8: 15 | D8: =Assumptions!C23 -> 5000 | E8: =2000+(C8*50) -> 2750 | F8: =C8*25 -> 375 | G8: =D8+E8+F8 -> 8125 | H8: =E8+F8 -> 3125
B9: Manitoba | C9: 15 | D9: =Assumptions!C23 -> 5000 | E9: =2000+(C9*50) -> 2750 | F9: =C9*25 -> 375 | G9: =D9+E9+F9 -> 8125 | H9: =E9+F9 -> 3125
B10: Ontario | C10: 120 | D10: =Assumptions!C23 -> 5000 | E10: =2000+(C10*50) -> 8000 | F10: =C10*25 -> 3000 | G10: =D10+E10+F10 -> 16000 | H10: =E10+F10 -> 11000
B11: Quebec | C11: 80 | D11: =Assumptions!C23 -> 5000 | E11: =2000+(C11*50) -> 6000 | F11: =C11*25 -> 2000 | G11: =D11+E11+F11 -> 13000 | H11: =E11+F11 -> 8000
B12: New Brunswick | C12: 10 | D12: =Assumptions!C23 -> 5000 | E12: =2000+(C12*50) -> 2500 | F12: =C12*25 -> 250 | G12: =D12+E12+F12 -> 7750 | H12: =E12+F12 -> 2750
B13: Nova Scotia | C13: 12 | D13: =Assumptions!C23 -> 5000 | E13: =2000+(C13*50) -> 2600 | F13: =C13*25 -> 300 | G13: =D13+E13+F13 -> 7900 | H13: =E13+F13 -> 2900
B14: Prince Edward Island | C14: 5 | D14: =Assumptions!C23 -> 5000 | E14: =2000+(C14*50) -> 2250 | F14: =C14*25 -> 125 | G14: =D14+E14+F14 -> 7375 | H14: =E14+F14 -> 2375
B15: Newfoundland & Labrador | C15: 8 | D15: =Assumptions!C23 -> 5000 | E15: =2000+(C15*50) -> 2400 | F15: =C15*25 -> 200 | G15: =D15+E15+F15 -> 7600 | H15: =E15+F15 -> 2600
B16: Northern Territories | C16: 5 | D16: =Assumptions!C23 -> 5000 | E16: =2000+(C16*50) -> 2250 | F16: =C16*25 -> 125 | G16: =D16+E16+F16 -> 7375 | H16: =E16+F16 -> 2375
B17: TOTAL (All Regions) | C17: =SUM(C6:C16) -> 345 | D17: =SUM(D6:D16) -> 55000 | E17: =SUM(E6:E16) -> 39250 | F17: =SUM(F6:F16) -> 8625 | G17: =SUM(G6:G16) -> 102875 | H17: =SUM(H6:H16) -> 47875
B20: Deployment Cost Summary
B21: Total One-Time Implementation | C21: =SUM(D6:D16) -> 55000
B22: Total Annual Recurring (per region) | C22: =SUM(H6:H16) -> 47875
B23: Avg. Cost per Region (Year 1) | C23: =G17/11 -> 9352.2727

Sheet Revenue Model
B2: 3-Year Revenue Projection
B4: Customer Acquisition Scenarios
C5: Year 1 | D5: Year 2 | E5: Year 3
B6: National Union Clients
B7: New Enterprise Clients (50k+) | C7: 1 | D7: 1 | E7: 2
B8: New Premium Clients (15k-50k) | C8: 2 | D8: 3 | E8: 4
B9: New Professional Clients (2k-15k) | C9: 3 | D9: 5 | E9: 6
B10: New Starter Clients (<2k) | C10: 2 | D10: 3 | E10: 4
B11: Cumulative Clients | C11: =SUM(C7:C10) -> 8 | D11: =C11+SUM(D7:D10) -> 20 | E11: =D11+SUM(E7:E10) -> 36
B13: Average Members per Tier
B14: Avg. Enterprise Members | C14: 75000
B15: Avg. Premium Members | C15: 30000
B16: Avg. Professional Members | C16: 8000
B17: Avg. Starter Members | C17: 1000
B19: Revenue Breakdown (CAD)
B20: Revenue Stream | C20: Year 1 | D20: Year 2 | E20: Year 3
B21: Enterprise Per-Member Revenue | C21: =C7*$C$14*'Tier Pricing'!E6 -> 4050000 | D21: =SUM(C7:D7)*$C$14*'Tier Pricing'!E6*(1+Assumptions!C24)^1 -> 8343000 | E21: =SUM(C7:E7)*$C$14*'Tier Pricing'!E6*(1+Assumptions!C24)^2 -> 17186580
B22: Premium Per-Member Revenue | C22: =C8*$C$15*'Tier Pricing'!E7 -> 2700000 | D22: =SUM(C8:D8)*$C$15*'Tier Pricing'!E7*(1+Assumptions!C24)^1 -> 6952500 | E22: =SUM(C8:E8)*$C$15*'Tier Pricing'!E7*(1+Assumptions!C24)^2 -> 12889935
B23: Professional Per-Member Revenue | C23: =C9*$C$16*'Tier Pricing'!E8 -> 849600 | D23: =SUM(C9:D9)*$C$16*'Tier Pricing'!E8*(1+Assumptions!C24)^1 -> 2333568 | E23: =SUM(C9:E9)*$C$16*'Tier Pricing'!E8*(1+Assumptions!C24)^2 -> 4206256.3
B24: Starter Per-Member Revenue | C24: =C10*$C$17*'Tier Pricing'!E9 -> 54000 | D24: =SUM(C10:D10)*$C$17*'Tier Pricing'!E9*(1+Assumptions!C24)^1 -> 139050 | E24: =SUM(C10:E10)*$C$17*'Tier Pricing'!E9*(1+Assumptions!C24)^2 -> 257798.7
B25: National License Base Fees | C25: =C11*Assumptions!C22 -> 200000 | D25: =D11*Assumptions!C22 -> 500000 | E25: =E11*Assumptions!C22 -> 900000
B26: Implementation Fees (One-Time) | C26: =(SUM(C7:C10))*10*Assumptions!C23 -> 400000 | D26: =(SUM(D7:D10))*10*Assumptions!C23 -> 600000 | E26: =(SUM(E7:E10))*10*Assumptions!C23 -> 800000
B27: Regional Deployment Revenue | C27: =C11*'Regional Deploy'!H17/1 -> 383000 | D27: =D11*'Regional Deploy'!H17/1 -> 957500 | E27: =E11*'Regional Deploy'!H17/1 -> 1723500
B28: TOTAL REVENUE | C28: =SUM(C21:C27) -> 8636600 | D28: =SUM(D21:D27) -> 19825618 | E28: =SUM(E21:E27) -> 37964070
B30: Cost Breakdown (CAD)
B31: Cost Item | C31: Year 1 | D31: Year 2 | E31: Year 3
B32: Fixed Costs (from Assumptions) | C32: =Assumptions!C17 -> 978000 | D32: =Assumptions!C17*(1+0.05*1) -> 1026900 | E32: =Assumptions!C17*(1+0.05*2) -> 1075800
B33: Variable Costs (Per-Member) | C33: =(C7*$C$14+C8*$C$15+C9*$C$16+C10*$C$17)*Assumptions!C15*12 -> 289800 | D33: =(SUM(C7:D7)*$C$14+SUM(C8:D8)*$C$15+SUM(C9:D9)*$C$16+SUM(C10:D10)*$C$17)*Assumptions!C15*12 -> 664200 | E33: =(SUM(C7:E7)*$C$14+SUM(C8:E8)*$C$15+SUM(C9:E9)*$C$16+SUM(C10:E10)*$C$17)*Assumptions!C15*12 -> 1243800
B34: Implementation Costs | C34: =(SUM(C7:C10))*10*Assumptions!C14 -> 280000 | D34: =(SUM(D7:D10))*10*Assumptions!C14 -> 420000 | E34: =(SUM(E7:E10))*10*Assumptions!C14 -> 560000
B35: Regional Deployment Costs | C35: ='Regional Deploy'!G17 -> 102875 | D35: ='Regional Deploy'!H17*D11 -> 957500 | E35: ='Regional Deploy'!H17*E11 -> 1723500
B36: TOTAL COSTS | C36: =SUM(C32:C35) -> 1650675 | D36: =SUM(D32:D35) -> 3068600 | E36: =SUM(E32:E35) -> 4603100
B38: NET PROFIT / (LOSS) | C38: =C28-C36 -> 6985925 | D38: =D28-D36 -> 16757018 | E38: =E28-E36 -> 33360970
B39: Gross Margin | C39: =IF(C28=0,0,C38/C28) -> 0.80887444 | D39: =IF(D28=0,0,D38/D28) -> 0.84522046 | E39: =IF(E28=0,0,E38/E28) -> 0.87875115

Sheet Breakeven
B2: Breakeven Analysis
B4: Breakeven by Member Count
B5: Calculates the minimum number of members needed to cover all fixed + variable costs at each tier's pricing.
B6: Metric | C6: Starter | D6: Professional | E6: Premium | F6: Enterprise
B7: Annual Per-Member Price | C7: ='Tier Pricing'!E6 -> 54 | D7: ='Tier Pricing'!E7 -> 45 | E7: ='Tier Pricing'!E8 -> 35.4 | F7: ='Tier Pricing'!E9 -> 27
B8: Annual Variable Cost / Member | C8: =Assumptions!C15*12 -> 1.8 | D8: =Assumptions!C15*12 -> 1.8 | E8: =Assumptions!C15*12 -> 1.8 | F8: =Assumptions!C15*12 -> 1.8
B9: Contribution Margin / Member | C9: =C7-C8 -> 52.2 | D9: =D7-D8 -> 43.2 | E9: =E7-E8 -> 33.6 | F9: =F7-F8 -> 25.2
B10: Total Annual Fixed Costs | C10: =Assumptions!C17 -> 978000 | D10: =Assumptions!C17 -> 978000 | E10: =Assumptions!C17 -> 978000 | F10: =Assumptions!C17 -> 978000
B11: National Base Fee (per client) | C11: =Assumptions!C22 -> 25000 | D11: =Assumptions!C22 -> 25000 | E11: =Assumptions!C22 -> 25000 | F11: =Assumptions!C22 -> 25000
B13: BREAKEVEN MEMBERS (1 Client) | C13: =IF(C9<=0,"N/A",ROUNDUP((C10-C11)/C9,0)) -> 18257 | D13: =IF(D9<=0,"N/A",ROUNDUP((D10-D11)/D9,0)) -> 22061 | E13: =IF(E9<=0,"N/A",ROUNDUP((E10-E11)/E9,0)) -> 28364 | F13: =IF(F9<=0,"N/A",ROUNDUP((F10-F11)/F9,0)) -> 37818
B14: Breakeven with 3 Clients | C14: =IF(C9<=0,"N/A",ROUNDUP((C10-3*C11)/(3*C9),0)) -> 5767 | D14: =IF(D9<=0,"N/A",ROUNDUP((D10-3*D11)/(3*D9),0)) -> 6968 | E14: =IF(E9<=0,"N/A",ROUNDUP((E10-3*E11)/(3*E9),0)) -> 8959 | F14: =IF(F9<=0,"N/A",ROUNDUP((F10-3*F11)/(3*F9),0)) -> 11945
B15: Breakeven with 5 Clients | C15: =IF(C9<=0,"N/A",ROUNDUP((C10-5*C11)/(5*C9),0)) -> 3269 | D15: =IF(D9<=0,"N/A",ROUNDUP((D10-5*D11)/(5*D9),0)) -> 3950 | E15: =IF(E9<=0,"N/A",ROUNDUP((E10-5*E11)/(5*E9),0)) -> 5078 | F15: =IF(F9<=0,"N/A",ROUNDUP((F10-5*F11)/(5*F9),0)) -> 6770
B18: Revenue Sensitivity (Annual, per Client)
B19: Shows annual revenue at various member counts for each tier — use to identify sweet spots.
B20: Members | C20: Starter Rev | D20: Professional Rev | E20: Premium Rev | F20: Enterprise Rev | G20: Avg. Cost
B21: 200 | C21: =Assumptions!C22+B21*'Tier Pricing'!E6 -> 35800 | D21: =Assumptions!C22+B21*'Tier Pricing'!E7 -> 34000 | E21: =Assumptions!C22+B21*'Tier Pricing'!E8 -> 32080 | F21: =Assumptions!C22+B21*'Tier Pricing'!E9 -> 30400 | G21: =Assumptions!C17/3+B21*Assumptions!C15*12 -> 326360
B22: 500 | C22: =Assumptions!C22+B22*'Tier Pricing'!E6 -> 52000 | D22: =Assumptions!C22+B22*'Tier Pricing'!E7 -> 47500 | E22: =Assumptions!C22+B22*'Tier Pricing'!E8 -> 42700 | F22: =Assumptions!C22+B22*'Tier Pricing'!E9 -> 38500 | G22: =Assumptions!C17/3+B22*Assumptions!C15*12 -> 326900
B23: 1000 | C23: =Assumptions!C22+B23*'Tier Pricing'!E6 -> 79000 | D23: =Assumptions!C22+B23*'Tier Pricing'!E7 -> 70000 | E23: =Assumptions!C22+B23*'Tier Pricing'!E8 -> 60400 | F23: =Assumptions!C22+B23*'Tier Pricing'!E9 -> 52000 | G23: =Assumptions!C17/3+B23*Assumptions!C15*12 -> 327800
B24: 2000 | C24: =Assumptions!C22+B24*'Tier Pricing'!E6 -> 133000 | D24: =Assumptions!C22+B24*'Tier Pricing'!E7 -> 115000 | E24: =Assumptions!C22+B24*'Tier Pricing'!E8 -> 95800 | F24: =Assumptions!C22+B24*'Tier Pricing'!E9 -> 79000 | G24: =Assumptions!C17/3+B24*Assumptions!C15*12 -> 329600
B25: 5000 | C25: =Assumptions!C22+B25*'Tier Pricing'!E6 -> 295000 | D25: =Assumptions!C22+B25*'Tier Pricing'!E7 -> 250000 | E25: =Assumptions!C22+B25*'Tier Pricing'!E8 -> 202000 | F25: =Assumptions!C22+B25*'Tier Pricing'!E9 -> 160000 | G25: =Assumptions!C17/3+B25*Assumptions!C15*12 -> 335000
B26: 10000 | C26: =Assumptions!C22+B26*'Tier Pricing'!E6 -> 565000 | D26: =Assumptions!C22+B26*'Tier Pricing'!E7 -> 475000 | E26: =Assumptions!C22+B26*'Tier Pricing'!E8 -> 379000 | F26: =Assumptions!C22+B26*'Tier Pricing'!E9 -> 295000 | G26: =Assumptions!C17/3+B26*Assumptions!C15*12 -> 344000
B27: 15000 | C27: =Assumptions!C22+B27*'Tier Pricing'!E6 -> 835000 | D27: =Assumptions!C22+B27*'Tier Pricing'!E7 -> 700000 | E27: =Assumptions!C22+B27*'Tier Pricing'!E8 -> 556000 | F27: =Assumptions!C22+B27*'Tier Pricing'!E9 -> 430000 | G27: =Assumptions!C17/3+B27*Assumptions!C15*12 -> 353000
B28: 25000 | C28: =Assumptions!C22+B28*'Tier Pricing'!E6 -> 1375000 | D28: =Assumptions!C22+B28*'Tier Pricing'!E7 -> 1150000 | E28: =Assumptions!C22+B28*'Tier Pricing'!E8 -> 910000 | F28: =Assumptions!C22+B28*'Tier Pricing'!E9 -> 700000 | G28: =Assumptions!C17/3+B28*Assumptions!C15*12 -> 371000
B29: 50000 | C29: =Assumptions!C22+B29*'Tier Pricing'!E6 -> 2725000 | D29: =Assumptions!C22+B29*'Tier Pricing'!E7 -> 2275000 | E29: =Assumptions!C22+B29*'Tier Pricing'!E8 -> 1795000 | F29: =Assumptions!C22+B29*'Tier Pricing'!E9 -> 1375000 | G29: =Assumptions!C17/3+B29*Assumptions!C15*12 -> 416000
B30: 75000 | C30: =Assumptions!C22+B30*'Tier Pricing'!E6 -> 4075000 | D30: =Assumptions!C22+B30*'Tier Pricing'!E7 -> 3400000 | E30: =Assumptions!C22+B30*'Tier Pricing'!E8 -> 2680000 | F30: =Assumptions!C22+B30*'Tier Pricing'!E9 -> 2050000 | G30: =Assumptions!C17/3+B30*Assumptions!C15*12 -> 461000
B31: 100000 | C31: =Assumptions!C22+B31*'Tier Pricing'!E6 -> 5425000 | D31: =Assumptions!C22+B31*'Tier Pricing'!E7 -> 4525000 | E31: =Assumptions!C22+B31*'Tier Pricing'!E8 -> 3565000 | F31: =Assumptions!C22+B31*'Tier Pricing'!E9 -> 2725000 | G31: =Assumptions!C17/3+B31*Assumptions!C15*12 -> 506000
B60: Note: Breakeven assumes all fixed costs must be covered by per-member revenue after subtracting base fees. With more clients sharing fixed costs, per-client breakeven drops significantly.
B61: Model generated: 2026-04-02 | All values in CAD
